{
  "formatVersion": "1",
  "header": {
    "description": "Compare Supplier Quotations",
    "originalLanguage": "en",
    "abapLanguageVersion": "cloudDevelopment"
  },
  "generalInformation": {
    "appType": "ui5",
    "catalogId": "SAP_TC_UI5_REPO_UIAD"
  },
  "ui5AppDetails": {
    "appId": "zfcustomsupquotcomp"
  },
  "navigation": {
    "targetMappingId": "UI5R_D9ADBD0B6EA00663A1196FEB007EDC576B45F82C_TM",
    "semanticObject": "zfcomsupquot",
    "action": "display",
    "desktop": true,
    "tablet": true,
    "phone": true
  },
  "tiles": [
    {
      "id": "UI5R_D9ADBD0B6EA00663A1196FEB007EDC576B45F82C_AL",
      "tileType": "static",
      "isDefault": true,
      "standard": {
        "title": "Compare Supplier Quotations",
        "subtitle": "Custom Application"
      }
    }
  ]
}
